{
    "Case Title": " Union of India, Ministry of Law & Justice  Vs Justice (Retd) Raj Rahul Garg (Raj Rani Jain) and Others",
    "Citation": "[2024] 3 S.C.R. 848",
    "Judges": "D.Y. CHANDRACHUD,J.B. PARDIWALA,Manoj Misra",
    "Issue for Consideration": "Issue for Consideration Whether gap between the retirement of a District Judge and her subsequent appointment as the Judge of the High Court would constitute \u2018break in service\u2019 adversely affecting her benefits. Headnotes The High Court Judges (Salaries and Conditions of Service) Act, 1954 \u2013 s. 14, 15, Para 2, Part III of the First Schedule \u2013 Entitlement of High Court Judge promoted from District Judiciary to pension and retirement benefits despite break in service \u2013",
    "Headnotes": "The High Court Judges (Salaries and Conditions of Service) Act, 1954 &ndash; s. 14, 15, Para 2, Part III of the First Schedule &ndash; Entitlement of High Court Judge promoted from District Judiciary to pension and retirement benefits despite break in service &ndash;<br>",
    "Decision Date": " 15-03-2024",
    "Case Number": " CIVIL APPEAL/4272/2024",
    "Disposal Nature": " Disposed off",
    "Direction Issue": ""
}